PyEvoMotion/__init__.py
PyEvoMotion/cli.py
PyEvoMotion/core/__init__.py
PyEvoMotion/core/base.py
PyEvoMotion/core/core.py
PyEvoMotion/core/parser.py
PyEvoMotion/utils.py
share/analyze_model_selection_accuracy.py
share/anomalous_diffusion.pdf
share/confusion_matrix_heatmap.pdf
share/figUK.tsv
share/figUK_plots.pdf
share/figUK_regression_results.json
share/figUK_run_args.json
share/figUK_stats.tsv
share/figUSA.tsv
share/figUSA_plots.pdf
share/figUSA_regression_results.json
share/figUSA_run_args.json
share/figUSA_stats.tsv
share/figdataUK.tsv
share/figdataUSA.tsv
share/figure.pdf
share/generate_sequences_from_synthdata.py
share/generate_sequences_from_test5_data.py
share/mafft_install.sh
share/manuscript_figure.py
share/run_parallel_analysis.py
share/synth_figure.pdf
share/uk_time_windows.pdf
share/weekly_size.pdf
pyevomotion-0.1.3.dist-info/METADATA
pyevomotion-0.1.3.dist-info/WHEEL
pyevomotion-0.1.3.dist-info/entry_points.txt
pyevomotion-0.1.3.dist-info/RECORD
