Metadata-Version: 2.3
Name: PyEvoMotion
Version: 0.1.3
Summary: Evolutionary motion analysis tool
Keywords: evolution,anomalous diffusion,bioinformatics
Author: Lucas Goiriz
Author-email: lucas.goiriz@csic.es
Requires-Python: >=3.12,<3.13
Classifier: Programming Language :: Python :: 3
Classifier: Programming Language :: Python :: 3.12
Requires-Dist: bio (>=1.7.1,<2.0.0)
Requires-Dist: matplotlib (>=3.9.1,<4.0.0)
Requires-Dist: pandas (>=2.2.2,<3.0.0)
Requires-Dist: pytest (>=8.2.2,<9.0.0)
Requires-Dist: scikit-learn (>=1.5.1,<2.0.0)
Requires-Dist: twine (>=6.1.0,<7.0.0)
Project-URL: Homepage, https://luksgrin.github.io/PyEvoMotion/
Project-URL: Repository, https://github.com/luksgrin/PyEvoMotion/
